{
	"sni_dnsnames": [
		""
	],
	"csr_cn": "",
	"csr_c": "",
	"csr_st": "",
	"csr_l": "",
	"csr_o": "",
	"csr_ou": "",
	"csr_sans": [
		""
	],
	"org_name": "",
	"org_addressLineOne": "",
	"org_addressLineTwo": "",
	"org_city": "",
	"org_region": "",
	"org_postalCode": "",
	"org_country": "",
	"org_phone": "",
	"admincontact_firstName": "",
	"admincontact_lastName": "",
	"admincontact_phone": "",
	"admincontact_email": "",
	"admincontact_addressLineOne": "",
	"admincontact_addressLineTwo": "",
	"admincontact_city": "",
	"admincontact_country": "",
	"admincontact_organizationName": "",
	"admincontact_postalCode": "",
	"admincontact_region": "",
	"admincontact_title": "",
	"techcontact_firstName": "",
	"techcontact_lastName": "",
	"techcontact_phone": "",
	"techcontact_email": "",
	"techcontact_addressLineOne": "",
	"techcontact_addressLineTwo": "",
	"techcontact_city": "",
	"techcontact_country": "",
	"techcontact_organizationName": "",
	"techcontact_postalCode": "",
	"techcontact_region": "",
	"techcontact_title": ""
}
